scrainbow/__init__.py
scrainbow/data_processing.py
scrainbow/model.py
scrainbow/run.py
scrainbow/run_getNcluster.py
scrainbow/run_refer_bulk.py
scrainbow/utils.py
scrainbow-0.0.2.dist-info/LICENSE
scrainbow-0.0.2.dist-info/METADATA
scrainbow-0.0.2.dist-info/WHEEL
scrainbow-0.0.2.dist-info/top_level.txt
scrainbow-0.0.2.dist-info/RECORD
